aider.py
shell_aider-0.1.1.dist-info/LICENSE
shell_aider-0.1.1.dist-info/METADATA
shell_aider-0.1.1.dist-info/WHEEL
shell_aider-0.1.1.dist-info/entry_points.txt
shell_aider-0.1.1.dist-info/top_level.txt
shell_aider-0.1.1.dist-info/RECORD
