Metadata-Version: 2.1
Name: shell-aider
Version: 0.1.1
Summary: AI-powered shell assistant that uses tmux
Author-email: Elijah Knaperek <elijahknaperek@gmail.com>
License: GPLv3
Project-URL: Homepage, https://github.com/elijahknaperek/shell-aider
Keywords: ai,shell,tmux,assistant,terminal
Classifier: License :: OSI Approved :: GNU General Public License v3 (GPLv3)
Classifier: Programming Language :: Python
Classifier: Programming Language :: Python :: 3
Classifier: Environment :: Console
Requires-Python: >=3.8
License-File: LICENSE
Requires-Dist: litellm>=1.0.0
Requires-Dist: beautifulsoup4>=4.12.0
Requires-Dist: requests>=2.31.0
